qwikidata/__init__.py
qwikidata/claim.py
qwikidata/datavalue.py
qwikidata/entity.py
qwikidata/json_dump.py
qwikidata/linked_data_interface.py
qwikidata/snak.py
qwikidata/sparql.py
qwikidata/typedefs.py
qwikidata/utils.py
qwikidata-0.4.1.dist-info/AUTHORS.rst
qwikidata-0.4.1.dist-info/LICENSE
qwikidata-0.4.1.dist-info/METADATA
qwikidata-0.4.1.dist-info/WHEEL
qwikidata-0.4.1.dist-info/top_level.txt
qwikidata-0.4.1.dist-info/RECORD
